sullyai/__init__.py
sullyai/_base_client.py
sullyai/_client.py
sullyai/_compat.py
sullyai/_constants.py
sullyai/_exceptions.py
sullyai/_files.py
sullyai/_models.py
sullyai/_qs.py
sullyai/_resource.py
sullyai/_response.py
sullyai/_streaming.py
sullyai/_types.py
sullyai/_version.py
sullyai/py.typed
sullyai/_utils/__init__.py
sullyai/_utils/_logs.py
sullyai/_utils/_proxy.py
sullyai/_utils/_reflection.py
sullyai/_utils/_resources_proxy.py
sullyai/_utils/_streams.py
sullyai/_utils/_sync.py
sullyai/_utils/_transform.py
sullyai/_utils/_typing.py
sullyai/_utils/_utils.py
sullyai/lib/.keep
sullyai/resources/__init__.py
sullyai/resources/note_styles.py
sullyai/resources/notes.py
sullyai/resources/audio/__init__.py
sullyai/resources/audio/audio.py
sullyai/resources/audio/transcriptions/__init__.py
sullyai/resources/audio/transcriptions/stream.py
sullyai/resources/audio/transcriptions/transcriptions.py
sullyai/types/__init__.py
sullyai/types/delete_response.py
sullyai/types/note_create_params.py
sullyai/types/note_create_response.py
sullyai/types/note_retrieve_response.py
sullyai/types/note_style_create_params.py
sullyai/types/note_style_create_response.py
sullyai/types/audio/__init__.py
sullyai/types/audio/transcription_create_params.py
sullyai/types/audio/transcription_create_response.py
sullyai/types/audio/transcription_retrieve_response.py
sullyai/types/audio/transcriptions/__init__.py
sullyai/types/audio/transcriptions/stream_create_token_params.py
sullyai/types/audio/transcriptions/stream_create_token_response.py
sullyai/types/shared/__init__.py
sullyai/types/shared/heading_section.py
sullyai/types/shared/section.py
sullyai-0.1.0a10.dist-info/METADATA
sullyai-0.1.0a10.dist-info/WHEEL
sullyai-0.1.0a10.dist-info/licenses/LICENSE
sullyai-0.1.0a10.dist-info/RECORD
